{
  "version": "1.0",
  "description": "成人标签库 - 公共场所剧情 第7批",
  "tags": [
    {
      "id": 301,
      "内容": "超市货架间真空裙底被保安按墙上干到腿抖，精液射进阴道",
      "触发条件": ["超市", "货架", "真空", "保安", "干"],
      "阶段": 3,
      "尺度": "重",
      "权重": 0.9
    },
    {
      "id": 302,
      "内容": "商场自动扶梯上故意走光被多人手机偷拍，裙底真空乳头凸起",
      "触发条件": ["商场", "扶梯", "走光", "偷拍", "真空"],
      "阶段": 2,
      "尺度": "中",
      "权重": 0.7
    },
    {
      "id": 303,
      "内容": "咖啡厅卡座下脱内裤自慰被服务员跪舔阴道加入，精液射进阴道",
      "触发条件": ["咖啡厅", "卡座", "自慰", "服务员", "舔", "加入"],
      "阶段": 3,
      "尺度": "重",
      "权重": 0.9
    },
    {
      "id": 304,
      "内容": "公园野餐毯上被从后面顶入喷到草地，潮吹喷水",
      "触发条件": ["公园", "野餐", "后面", "顶入", "潮吹"],
      "阶段": 2,
      "尺度": "中",
      "权重": 0.7
    },
    {
      "id": 305,
      "内容": "地铁末班车空车厢被前后夹击，双洞轮流内射",
      "触发条件": ["地铁", "末班车", "前后夹击", "双洞"],
      "阶段": 3,
      "尺度": "重",
      "权重": 0.9
    },
    {
      "id": 306,
      "内容": "公交车拥挤中阴茎滑进湿阴道全程不拔，精液射进深处",
      "触发条件": ["公交车", "拥挤", "阴茎", "湿阴道", "全程不拔"],
      "阶段": 3,
      "尺度": "重",
      "权重": 0.8
    },
    {
      "id": 307,
      "内容": "电梯停电漆黑撕开丝袜后入到潮吹，精液射进阴道",
      "触发条件": ["电梯", "停电", "漆黑", "丝袜", "后入"],
      "阶段": 3,
      "尺度": "重",
      "权重": 0.8
    },
    {
      "id": 308,
      "内容": "电影院情侣座黑暗中手伸进裙子扣到喷座椅，爱液浸湿",
      "触发条件": ["电影院", "情侣座", "黑暗", "手伸进", "扣", "喷"],
      "阶段": 2,
      "尺度": "中",
      "权重": 0.7
    },
    {
      "id": 309,
      "内容": "KTV小包厢轮流坐脸舔到尿失禁，每个人都舔到喷尿",
      "触发条件": ["KTV", "小包厢", "轮流", "坐脸", "舔", "尿失禁"],
      "阶段": 3,
      "尺度": "重",
      "权重": 0.9
    },
    {
      "id": 310,
      "内容": "公司茶水间流理台按着猛插颜射咖啡杯，精液射进咖啡喝掉",
      "触发条件": ["公司", "茶水间", "流理台", "猛插", "颜射", "咖啡"],
      "阶段": 3,
      "尺度": "重",
      "权重": 0.8
    },
    {
      "id": 311,
      "内容": "健身房跑步机震动阴蒂到连续喷水",
      "触发条件": ["健身房", "跑步机", "震动", "阴蒂", "喷水"],
      "阶段": 2,
      "尺度": "中",
      "权重": 0.6
    },
    {
      "id": 312,
      "内容": "游泳池浅水区水下教练手指扩张到三指",
      "触发条件": ["游泳池", "浅水区", "水下", "教练", "手指", "扩张"],
      "阶段": 2,
      "尺度": "中",
      "权重": 0.7
    },
    {
      "id": 313,
      "内容": "试衣间三面镜自慰被店员推门撞见直接加入，两人一起自慰",
      "触发条件": ["试衣间", "三面镜", "自慰", "店员", "加入"],
      "阶段": 2,
      "尺度": "中",
      "权重": 0.7
    },
    {
      "id": 314,
      "内容": "公共厕所隔间门虚掩被路人推入轮流使用，被多人插入",
      "触发条件": ["公共厕所", "隔间", "虚掩", "路人", "轮流", "多人"],
      "阶段": 3,
      "尺度": "重",
      "权重": 0.9
    },
    {
      "id": 315,
      "内容": "公园长椅下69被遛狗大爷看到加入一起舔阴道",
      "触发条件": ["公园", "长椅", "69", "遛狗", "加入", "舔"],
      "阶段": 2,
      "尺度": "中",
      "权重": 0.7
    },
    {
      "id": 316,
      "内容": "图书馆死角书架后快速口爆吞精，若无其事继续看书",
      "触发条件": ["图书馆", "死角", "书架", "口爆", "吞精"],
      "阶段": 2,
      "尺度": "中",
      "权重": 0.6
    },
    {
      "id": 317,
      "内容": "医院候诊椅上护士偷偷手交射精，精液射到裤子湿一片",
      "触发条件": ["医院", "候诊椅", "护士", "手交", "射精"],
      "阶段": 2,
      "尺度": "中",
      "权重": 0.7
    },
    {
      "id": 318,
      "内容": "美容院激光脱毛时阴部震动到高潮喷",
      "触发条件": ["美容院", "激光脱毛", "阴部", "震动", "高潮"],
      "阶段": 2,
      "尺度": "中",
      "权重": 0.7
    },
    {
      "id": 319,
      "内容": "按摩店泰式油推直接滑入无套内射，精液射进阴道",
      "触发条件": ["按摩店", "泰式油推", "滑入", "无套", "内射"],
      "阶段": 3,
      "尺度": "重",
      "权重": 0.8
    },
    {
      "id": 320,
      "内容": "牙医治疗椅被塞阴茎颜射口腔，精液顺着嘴角流到脖子",
      "触发条件": ["牙医", "治疗椅", "阴茎", "颜射", "口腔"],
      "阶段": 3,
      "尺度": "重",
      "权重": 0.8
    },
    {
      "id": 321,
      "内容": "理发店围布下手淫射精射到镜子上，精液缓缓往下滴",
      "触发条件": ["理发店", "围布", "手淫", "射精", "镜子"],
      "阶段": 2,
      "尺度": "中",
      "权重": 0.6
    },
    {
      "id": 322,
      "内容": "网吧黑暗包间看A片被后入到喷，键盘上全是爱液",
      "触发条件": ["网吧", "黑暗", "包间", "A片", "后入", "喷"],
      "阶段": 2,
      "尺度": "中",
      "权重": 0.7
    },
    {
      "id": 323,
      "内容": "游戏厅街机震动同步阴茎抽插到射精，精液射到裤子",
      "触发条件": ["游戏厅", "街机", "震动", "同步", "阴茎", "射精"],
      "阶段": 2,
      "尺度": "中",
      "权重": 0.6
    },
    {
      "id": 324,
      "内容": "停车场地下层车震被巡逻保安发现加入，三个人一起",
      "触发条件": ["停车场", "地下层", "车震", "保安", "加入", "三人"],
      "阶段": 3,
      "尺度": "重",
      "权重": 0.9
    },
    {
      "id": 325,
      "内容": "高速服务区厕所被卡门缝里猛干到喷，精液滴到马桶",
      "触发条件": ["服务区", "厕所", "门缝", "猛干", "喷"],
      "阶段": 2,
      "尺度": "中",
      "权重": 0.7
    },
    {
      "id": 326,
      "内容": "绿皮火车硬座被乘客从后面顶到高潮，阴道被插入",
      "触发条件": ["火车", "硬座", "乘客", "后面", "顶", "高潮"],
      "阶段": 2,
      "尺度": "中",
      "权重": 0.7
    },
    {
      "id": 327,
      "内容": "飞机经济舱厕所一英里俱乐部快速内射，精液射进阴道",
      "触发条件": ["飞机", "经济舱", "厕所", "一英里俱乐部", "内射"],
      "阶段": 2,
      "尺度": "中",
      "权重": 0.7
    },
    {
      "id": 328,
      "内容": "邮轮甲板深夜海风吹着狗爬式潮吹，海风吹着乳头",
      "触发条件": ["邮轮", "甲板", "深夜", "海风", "狗爬式", "潮吹"],
      "阶段": 2,
      "尺度": "中",
      "权重": 0.7
    },
    {
      "id": 329,
      "内容": "森林露营帐篷闷热整夜不拔到脱水，汗液混着爱液",
      "触发条件": ["森林", "露营", "帐篷", "闷热", "不拔"],
      "阶段": 2,
      "尺度": "中",
      "权重": 0.7
    },
    {
      "id": 330,
      "内容": "海滩礁石后浪拍打跪舔到吞精，精液射进嘴里",
      "触发条件": ["海滩", "礁石", "浪拍打", "跪舔", "吞精"],
      "阶段": 2,
      "尺度": "中",
      "权重": 0.7
    },
    {
      "id": 331,
      "内容": "温泉露天池被水下摸到插入，手指伸进阴道",
      "触发条件": ["温泉", "露天池", "水下", "摸", "插入"],
      "阶段": 2,
      "尺度": "中",
      "权重": 0.7
    },
    {
      "id": 332,
      "内容": "雪地露天温泉乳头冻硬被舔到痉挛，乳头被舔硬",
      "触发条件": ["雪地", "温泉", "乳头", "冻硬", "舔", "痉挛"],
      "阶段": 2,
      "尺度": "中",
      "权重": 0.7
    },
    {
      "id": 333,
      "内容": "桑拿高温房汗水混精液滴地板，形成小水洼",
      "触发条件": ["桑拿", "高温", "汗水", "精液", "地板"],
      "阶段": 2,
      "尺度": "中",
      "权重": 0.7
    },
    {
      "id": 334,
      "内容": "蒸汽浴玻璃墙贴身猛撞雾气精迹，精液粘玻璃上",
      "触发条件": ["蒸汽浴", "玻璃墙", "贴身", "猛撞", "精液"],
      "阶段": 2,
      "尺度": "中",
      "权重": 0.7
    },
    {
      "id": 335,
      "内容": "情趣酒店旋转床360度多角度内射，精液射到各个角度",
      "触发条件": ["情趣酒店", "旋转床", "360度", "多角度", "内射"],
      "阶段": 2,
      "尺度": "中",
      "权重": 0.7
    },
    {
      "id": 336,
      "内容": "SM主题房吊环吊起蜡烛滴阴唇到红肿，阴唇被滴红",
      "触发条件": ["SM主题房", "吊环", "蜡烛", "阴唇", "红肿"],
      "阶段": 3,
      "尺度": "重",
      "权重": 0.8
    },
    {
      "id": 337,
      "内容": "角色扮演办公室上司惩罚秘书撕丝袜，按办公桌插入",
      "触发条件": ["角色扮演", "办公室", "上司", "秘书", "丝袜", "插入"],
      "阶段": 2,
      "尺度": "中",
      "权重": 0.7
    },
    {
      "id": 338,
      "内容": "护士站推车被病人按着干到喷奶，乳汁喷射到病历本",
      "触发条件": ["护士站", "推车", "病人", "干", "喷奶"],
      "阶段": 2,
      "尺度": "中",
      "权重": 0.7
    },
    {
      "id": 339,
      "内容": "女仆咖啡厅桌子下跪地口爆主人，射精射到喉咙里",
      "触发条件": ["女仆咖啡厅", "桌子下", "跪地", "口爆", "喉咙"],
      "阶段": 2,
      "尺度": "中",
      "权重": 0.7
    },
    {
      "id": 340,
      "内容": "OL加班会议室关灯后被集体轮流，每人射一次",
      "触发条件": ["OL", "加班", "会议室", "关灯", "集体", "轮流"],
      "阶段": 3,
      "尺度": "重",
      "权重": 0.9
    },
    {
      "id": 341,
      "内容": "老板办公桌玻璃面内射后流精展示，精液顺着玻璃流",
      "触发条件": ["老板", "办公桌", "玻璃面", "内射", "流精"],
      "阶段": 2,
      "尺度": "中",
      "权重": 0.7
    },
    {
      "id": 342,
      "内容": "公司储藏室货架压着小幅度操到喷，精液滴到货架",
      "触发条件": ["储藏室", "货架", "压着", "小幅度", "操", "喷"],
      "阶段": 2,
      "尺度": "中",
      "权重": 0.6
    },
    {
      "id": 343,
      "内容": "家教课后学生把老师按课桌颜射，精液射到脸上",
      "触发条件": ["家教", "学生", "老师", "课桌", "颜射"],
      "阶段": 2,
      "尺度": "中",
      "权重": 0.7
    },
    {
      "id": 344,
      "内容": "补习班厕所镜子前互相扣到喷尿，尿液喷到镜子",
      "触发条件": ["补习班", "厕所", "镜子", "互相扣", "喷尿"],
      "阶段": 2,
      "尺度": "中",
      "权重": 0.7
    },
    {
      "id": 345,
      "内容": "大学宿舍阳台深夜室友抱操路人看，楼下人看到身影",
      "触发条件": ["大学宿舍", "阳台", "深夜", "室友", "抱操", "路人看"],
      "阶段": 2,
      "尺度": "中",
      "权重": 0.7
    },
    {
      "id": 346,
      "内容": "社团活动室道具间捆绑椅子上玩弄乳房，阴部被道具玩",
      "触发条件": ["社团", "活动室", "道具间", "捆绑", "椅子", "玩弄"],
      "阶段": 3,
      "尺度": "重",
      "权重": 0.8
    },
    {
      "id": 347,
      "内容": "毕业旅行温泉大浴场多人围观潮吹，水里都是人",
      "触发条件": ["毕业旅行", "温泉", "大浴场", "多人", "围观", "潮吹"],
      "阶段": 3,
      "尺度": "重",
      "权重": 0.8
    },
    {
      "id": 348,
      "内容": "同学聚会醉酒后集体开房灌精，精液灌到肚子里",
      "触发条件": ["同学聚会", "醉酒", "集体", "开房", "灌精"],
      "阶段": 3,
      "尺度": "重",
      "权重": 0.9
    },
    {
      "id": 349,
      "内容": "婚礼后台化妆间婚纱掀起伴郎内射，精液顺着婚纱流",
      "触发条件": ["婚礼后台", "化妆间", "婚纱", "掀起", "伴郎", "内射"],
      "阶段": 2,
      "尺度": "中",
      "权重": 0.7
    },
    {
      "id": 350,
      "内容": "婚纱摄影棚道具床被摄影师猛干，精液滴到裙摆",
      "触发条件": ["婚纱摄影棚", "道具床", "摄影师", "猛干", "精液"],
      "阶段": 2,
      "尺度": "中",
      "权重": 0.7
    }
  ]
}
